d3/__init__.py
d3/encoding.py
d3/preprocessing.py
d3/scaling.py
d3/utils.py
d3_ml-0.1.0.dist-info/METADATA
d3_ml-0.1.0.dist-info/WHEEL
d3_ml-0.1.0.dist-info/top_level.txt
d3_ml-0.1.0.dist-info/RECORD
