Metadata-Version: 2.4
Name: d3-ml
Version: 0.1.0
Summary: Simple ML preprocessing toolkit
Requires-Dist: pandas
Requires-Dist: scikit-learn
Dynamic: requires-dist
Dynamic: summary
